{
  "book_name": "Romans",
  "chapter": 15,
  "verses": [
    {
      "book_name": "Romans",
      "chapter": 15,
      "verse": 1,
      "text": "οφειλομεν δε ημεις οι δυνατοι τα ασθενηματα των αδυνατων βασταζειν και μη εαυτοις αρεσκειν",
      "header": "",
      "footer": ""
    },
    {
      "book_name": "Romans",
      "chapter": 15,
      "verse": 2,
      "text": "εκαστος γαρ ημων τω πλησιον αρεσκετω εις το αγαθον προς οικοδομην",
      "header": "",
      "footer": ""
    },
    {
      "book_name": "Romans",
      "chapter": 15,
      "verse": 3,
      "text": "και γαρ ο χριστος ουχ εαυτω ηρεσεν αλλα καθως γεγραπται οι ονειδισμοι των ονειδιζοντων σε επεπεσον επ εμε",
      "header": "",
      "footer": ""
    },
    {
      "book_name": "Romans",
      "chapter": 15,
      "verse": 4,
      "text": "οσα γαρ προεγραφη εις την ημετεραν διδασκαλιαν προεγραφη ινα δια της υπομονης και της παρακλησεως των γραφων την ελπιδα εχωμεν",
      "header": "",
      "footer": ""
    },
    {
      "book_name": "Romans",
      "chapter": 15,
      "verse": 5,
      "text": "ο δε θεος της υπομονης και της παρακλησεως δωη υμιν το αυτο φρονειν εν αλληλοις κατα χριστον ιησουν",
      "header": "",
      "footer": ""
    },
    {
      "book_name": "Romans",
      "chapter": 15,
      "verse": 6,
      "text": "ινα ομοθυμαδον εν ενι στοματι δοξαζητε τον θεον και πατερα του κυριου ημων ιησου χριστου",
      "header": "",
      "footer": ""
    },
    {
      "book_name": "Romans",
      "chapter": 15,
      "verse": 7,
      "text": "διο προσλαμβανεσθε αλληλους καθως και ο χριστος προσελαβετο ημας εις δοξαν θεου",
      "header": "",
      "footer": ""
    },
    {
      "book_name": "Romans",
      "chapter": 15,
      "verse": 8,
      "text": "λεγω δε ιησουν χριστον διακονον γεγενησθαι περιτομης υπερ αληθειας θεου εις το βεβαιωσαι τας επαγγελιας των πατερων",
      "header": "",
      "footer": ""
    },
    {
      "book_name": "Romans",
      "chapter": 15,
      "verse": 9,
      "text": "τα δε εθνη υπερ ελεους δοξασαι τον θεον καθως γεγραπται δια τουτο εξομολογησομαι σοι εν εθνεσιν και τω ονοματι σου ψαλω",
      "header": "",
      "footer": ""
    },
    {
      "book_name": "Romans",
      "chapter": 15,
      "verse": 10,
      "text": "και παλιν λεγει ευφρανθητε εθνη μετα του λαου αυτου",
      "header": "",
      "footer": ""
    },
    {
      "book_name": "Romans",
      "chapter": 15,
      "verse": 11,
      "text": "και παλιν αινειτε τον κυριον παντα τα εθνη και επαινεσατε αυτον παντες οι λαοι",
      "header": "",
      "footer": ""
    },
    {
      "book_name": "Romans",
      "chapter": 15,
      "verse": 12,
      "text": "και παλιν ησαιας λεγει εσται η ριζα του ιεσσαι και ο ανισταμενος αρχειν εθνων επ αυτω εθνη ελπιουσιν",
      "header": "",
      "footer": ""
    },
    {
      "book_name": "Romans",
      "chapter": 15,
      "verse": 13,
      "text": "ο δε θεος της ελπιδος πληρωσαι υμας πασης χαρας και ειρηνης εν τω πιστευειν εις το περισσευειν υμας εν τη ελπιδι εν δυναμει πνευματος αγιου",
      "header": "",
      "footer": ""
    },
    {
      "book_name": "Romans",
      "chapter": 15,
      "verse": 14,
      "text": "πεπεισμαι δε αδελφοι μου και αυτος εγω περι υμων οτι και αυτοι μεστοι εστε αγαθωσυνης πεπληρωμενοι πασης γνωσεως δυναμενοι και αλληλους νουθετειν",
      "header": "",
      "footer": ""
    },
    {
      "book_name": "Romans",
      "chapter": 15,
      "verse": 15,
      "text": "τολμηροτερον δε εγραψα υμιν αδελφοι απο μερους ως επαναμιμνησκων υμας δια την χαριν την δοθεισαν μοι υπο του θεου",
      "header": "",
      "footer": ""
    },
    {
      "book_name": "Romans",
      "chapter": 15,
      "verse": 16,
      "text": "εις το ειναι με λειτουργον ιησου χριστου εις τα εθνη ιερουργουντα το ευαγγελιον του θεου ινα γενηται η προσφορα των εθνων ευπροσδεκτος ηγιασμενη εν πνευματι αγιω",
      "header": "",
      "footer": ""
    },
    {
      "book_name": "Romans",
      "chapter": 15,
      "verse": 17,
      "text": "εχω ουν καυχησιν εν χριστω ιησου τα προς θεον",
      "header": "",
      "footer": ""
    },
    {
      "book_name": "Romans",
      "chapter": 15,
      "verse": 18,
      "text": "ου γαρ τολμησω λαλειν τι ων ου κατειργασατο χριστος δι εμου εις υπακοην εθνων λογω και εργω",
      "header": "",
      "footer": ""
    },
    {
      "book_name": "Romans",
      "chapter": 15,
      "verse": 19,
      "text": "εν δυναμει σημειων και τερατων εν δυναμει πνευματος θεου ωστε με απο ιερουσαλημ και κυκλω μεχρι του ιλλυρικου πεπληρωκεναι το ευαγγελιον του χριστου",
      "header": "",
      "footer": ""
    },
    {
      "book_name": "Romans",
      "chapter": 15,
      "verse": 20,
      "text": "ουτως δε φιλοτιμουμενον ευαγγελιζεσθαι ουχ οπου ωνομασθη χριστος ινα μη επ αλλοτριον θεμελιον οικοδομω",
      "header": "",
      "footer": ""
    },
    {
      "book_name": "Romans",
      "chapter": 15,
      "verse": 21,
      "text": "αλλα καθως γεγραπται οις ουκ ανηγγελη περι αυτου οψονται και οι ουκ ακηκοασιν συνησουσιν",
      "header": "",
      "footer": ""
    },
    {
      "book_name": "Romans",
      "chapter": 15,
      "verse": 22,
      "text": "διο και ενεκοπτομην τα πολλα του ελθειν προς υμας",
      "header": "",
      "footer": ""
    },
    {
      "book_name": "Romans",
      "chapter": 15,
      "verse": 23,
      "text": "νυνι δε μηκετι τοπον εχων εν τοις κλιμασιν τουτοις επιποθιαν δε εχων του ελθειν προς υμας απο πολλων ετων",
      "header": "",
      "footer": ""
    },
    {
      "book_name": "Romans",
      "chapter": 15,
      "verse": 24,
      "text": "ως εαν πορευωμαι εις την σπανιαν ελευσομαι προς υμας ελπιζω γαρ διαπορευομενος θεασασθαι υμας και υφ υμων προπεμφθηναι εκει εαν υμων πρωτον απο μερους εμπλησθω",
      "header": "",
      "footer": ""
    },
    {
      "book_name": "Romans",
      "chapter": 15,
      "verse": 25,
      "text": "νυνι δε πορευομαι εις ιερουσαλημ διακονων τοις αγιοις",
      "header": "",
      "footer": ""
    },
    {
      "book_name": "Romans",
      "chapter": 15,
      "verse": 26,
      "text": "ευδοκησαν γαρ μακεδονια και αχαια κοινωνιαν τινα ποιησασθαι εις τους πτωχους των αγιων των εν ιερουσαλημ",
      "header": "",
      "footer": ""
    },
    {
      "book_name": "Romans",
      "chapter": 15,
      "verse": 27,
      "text": "ευδοκησαν γαρ και οφειλεται αυτων εισιν ει γαρ τοις πνευματικοις αυτων εκοινωνησαν τα εθνη οφειλουσιν και εν τοις σαρκικοις λειτουργησαι αυτοις",
      "header": "",
      "footer": ""
    },
    {
      "book_name": "Romans",
      "chapter": 15,
      "verse": 28,
      "text": "τουτο ουν επιτελεσας και σφραγισαμενος αυτοις τον καρπον τουτον απελευσομαι δι υμων εις την σπανιαν",
      "header": "",
      "footer": ""
    },
    {
      "book_name": "Romans",
      "chapter": 15,
      "verse": 29,
      "text": "οιδα δε οτι ερχομενος προς υμας εν πληρωματι ευλογιας του ευαγγελιου του χριστου ελευσομαι",
      "header": "",
      "footer": ""
    },
    {
      "book_name": "Romans",
      "chapter": 15,
      "verse": 30,
      "text": "παρακαλω δε υμας αδελφοι δια του κυριου ημων ιησου χριστου και δια της αγαπης του πνευματος συναγωνισασθαι μοι εν ταις προσευχαις υπερ εμου προς τον θεον",
      "header": "",
      "footer": ""
    },
    {
      "book_name": "Romans",
      "chapter": 15,
      "verse": 31,
      "text": "ινα ρυσθω απο των απειθουντων εν τη ιουδαια και ινα η διακονια μου η εις ιερουσαλημ ευπροσδεκτος γενηται τοις αγιοις",
      "header": "",
      "footer": ""
    },
    {
      "book_name": "Romans",
      "chapter": 15,
      "verse": 32,
      "text": "ινα εν χαρα ελθω προς υμας δια θεληματος θεου και συναναπαυσωμαι υμιν",
      "header": "",
      "footer": ""
    },
    {
      "book_name": "Romans",
      "chapter": 15,
      "verse": 33,
      "text": "ο δε θεος της ειρηνης μετα παντων υμων αμην",
      "header": "",
      "footer": ""
    }
  ]
}