{
  "book_name": "Job",
  "chapter": 7,
  "verses": [
    {
      "book_name": "Job",
      "chapter": 7,
      "verse": 1,
      "text": "Is there not an appointed time to man vpon earth? are not his dayes also like the dayes of an hireling?",
      "header": "",
      "footer": ""
    },
    {
      "book_name": "Job",
      "chapter": 7,
      "verse": 2,
      "text": "As a seruant earnestly desireth the shadow, and as an hireling looketh for the reward of his worke:",
      "header": "",
      "footer": ""
    },
    {
      "book_name": "Job",
      "chapter": 7,
      "verse": 3,
      "text": "So am I made to possesse moneths of vanitie, and wearisome nights are appointed to me.",
      "header": "",
      "footer": ""
    },
    {
      "book_name": "Job",
      "chapter": 7,
      "verse": 4,
      "text": "When I lie downe, I say, When shall I arise, and the night be gone? and I am full of tossings to and fro, vnto the dawning of the day.",
      "header": "",
      "footer": ""
    },
    {
      "book_name": "Job",
      "chapter": 7,
      "verse": 5,
      "text": "My flesh is cloathed with wormes and clods of dust, my skinne is broken, and become loathsome.",
      "header": "",
      "footer": ""
    },
    {
      "book_name": "Job",
      "chapter": 7,
      "verse": 6,
      "text": "My dayes are swifter then a weauers shuttle, and are spent without hope.",
      "header": "",
      "footer": ""
    },
    {
      "book_name": "Job",
      "chapter": 7,
      "verse": 7,
      "text": "O remember that my life is winde: mine eye shall no more see good.",
      "header": "",
      "footer": ""
    },
    {
      "book_name": "Job",
      "chapter": 7,
      "verse": 8,
      "text": "The eye of him that hath seene me, shall see mee no more: thine eyes are vpon me, and I am not.",
      "header": "",
      "footer": ""
    },
    {
      "book_name": "Job",
      "chapter": 7,
      "verse": 9,
      "text": "As the cloud is consumed and vanisheth away: so he that goeth downe to the graue, shall come vp no more.",
      "header": "",
      "footer": ""
    },
    {
      "book_name": "Job",
      "chapter": 7,
      "verse": 10,
      "text": "Hee shall returne no more to his house: neither shall his place know him any more.",
      "header": "",
      "footer": ""
    },
    {
      "book_name": "Job",
      "chapter": 7,
      "verse": 11,
      "text": "Therefore I will not refraine my mouth, I wil speake in the anguish of my spirit, I will complaine in the bitternesse of my soule.",
      "header": "",
      "footer": ""
    },
    {
      "book_name": "Job",
      "chapter": 7,
      "verse": 12,
      "text": "Am I a sea, or a whale, that thou settest a watch ouer me?",
      "header": "",
      "footer": ""
    },
    {
      "book_name": "Job",
      "chapter": 7,
      "verse": 13,
      "text": "When I say, My bed shal comfort me, my couch shall ease my complaint:",
      "header": "",
      "footer": ""
    },
    {
      "book_name": "Job",
      "chapter": 7,
      "verse": 14,
      "text": "Then thou skarest mee with dreames, and terrifiest me through visions.",
      "header": "",
      "footer": ""
    },
    {
      "book_name": "Job",
      "chapter": 7,
      "verse": 15,
      "text": "So that my soule chooseth strangling: and death rather then my life.",
      "header": "",
      "footer": ""
    },
    {
      "book_name": "Job",
      "chapter": 7,
      "verse": 16,
      "text": "I loath it, I would not liue alway: let me alone, for my dayes are vanitie.",
      "header": "",
      "footer": ""
    },
    {
      "book_name": "Job",
      "chapter": 7,
      "verse": 17,
      "text": "What is man, that thou shouldest magnifie him? and that thou shouldest set thine heart vpon him?",
      "header": "",
      "footer": ""
    },
    {
      "book_name": "Job",
      "chapter": 7,
      "verse": 18,
      "text": "And that thou shouldest visite him euery morning, and trie him euery moment?",
      "header": "",
      "footer": ""
    },
    {
      "book_name": "Job",
      "chapter": 7,
      "verse": 19,
      "text": "How long wilt thou not depart from me? nor let me alone till I swallow downe my spittle?",
      "header": "",
      "footer": ""
    },
    {
      "book_name": "Job",
      "chapter": 7,
      "verse": 20,
      "text": "I haue sinned, what shall I doe vnto thee, O thou preseruer of men? why hast thou set me as a mark against thee, so that I am a burden to my selfe?",
      "header": "",
      "footer": ""
    },
    {
      "book_name": "Job",
      "chapter": 7,
      "verse": 21,
      "text": "And why doest thou not pardon my transgression, and take away mine iniquitie? for now shall I sleepe in the dust, and thou shalt seeke me in the morning, but I shall not be.",
      "header": "",
      "footer": ""
    }
  ]
}